{
  "id": "HealthKareAI/hospital/getDetails",
  "title": "Get Hospital Details API",
  "description": "POST /v1/hospital/details",
  "source": "@site/docs/HealthKareAI/hospital/getDetails.md",
  "sourceDirName": "HealthKareAI/hospital",
  "slug": "/HealthKareAI/hospital/getDetails",
  "permalink": "/docs/HealthKareAI/hospital/getDetails",
  "draft": false,
  "unlisted": false,
  "editUrl": "https://github.com/mellob1989/docs.noobsverse/tree/main/docs/HealthKareAI/hospital/getDetails.md",
  "tags": [],
  "version": "current",
  "frontMatter": {},
  "sidebar": "healthKareAI",
  "previous": {
    "title": "Verify Hospital OTP API",
    "permalink": "/docs/HealthKareAI/hospital/verifyOTP"
  },
  "next": {
    "title": "Error Codes and Security",
    "permalink": "/docs/HealthKareAI/error_codes"
  }
}